complexity/__init__.py
complexity/api/__init__.py
complexity/api/dataset.py
complexity/api/inference.py
complexity/api/model.py
complexity/api/multimodal.py
complexity/api/tokenizer.py
complexity/api/trainer.py
complexity/api/core/__init__.py
complexity/api/core/architecture.py
complexity/api/core/attention.py
complexity/api/core/block.py
complexity/api/core/cuda.py
complexity/api/core/efficient.py
complexity/api/core/helpers.py
complexity/api/core/mlp.py
complexity/api/core/norm.py
complexity/api/core/position.py
complexity/api/core/registry.py
complexity/cli/__init__.py
complexity/cli/app.py
complexity/cli/core.py
complexity/cli/utils.py
complexity/cli/commands/__init__.py
complexity/cli/commands/convert.py
complexity/cli/commands/inference.py
complexity/cli/commands/info.py
complexity/cli/commands/profile.py
complexity/cli/commands/serve.py
complexity/cli/commands/tokenize.py
complexity/cli/commands/train.py
complexity/config/__init__.py
complexity/config/model_config.py
complexity/core/__init__.py
complexity/core/registry.py
complexity/core/architectures/__init__.py
complexity/core/architectures/mamba.py
complexity/core/architectures/mixture_of_depths.py
complexity/core/architectures/retnet.py
complexity/core/architectures/rwkv.py
complexity/core/attention/__init__.py
complexity/core/attention/base.py
complexity/core/attention/flash_attention.py
complexity/core/attention/gqa.py
complexity/core/dynamics/__init__.py
complexity/core/dynamics/inl_dynamics.py
complexity/core/mlp/__init__.py
complexity/core/mlp/base.py
complexity/core/mlp/sparse_moe.py
complexity/core/mlp/standard.py
complexity/core/mlp/token_routed.py
complexity/core/normalization/__init__.py
complexity/core/normalization/norms.py
complexity/core/position/__init__.py
complexity/core/position/rotary.py
complexity/data/__init__.py
complexity/data/dataloader.py
complexity/data/preprocessing.py
complexity/data/streaming.py
complexity/data/tokenization.py
complexity/dataset/__init__.py
complexity_framework-0.3.0.dist-info/licenses/LICENSE
complexity_framework-0.3.0.dist-info/METADATA
complexity_framework-0.3.0.dist-info/WHEEL
complexity_framework-0.3.0.dist-info/entry_points.txt
complexity_framework-0.3.0.dist-info/top_level.txt
complexity_framework-0.3.0.dist-info/RECORD
