Metadata-Version: 2.4
Name: complexity-framework
Version: 0.3.0
Summary: Modular Python framework for building LLMs with INL Dynamics stability
Author-email: Complexity-ML <contact@complexity-ml.org>
License: CC-BY-NC-4.0
Project-URL: Homepage, https://github.com/Complexity-ML/complexity-framework
Project-URL: Documentation, https://github.com/Complexity-ML/complexity-framework/tree/main/docs
Project-URL: Repository, https://github.com/Complexity-ML/complexity-framework
Project-URL: Issues, https://github.com/Complexity-ML/complexity-framework/issues
Keywords: llm,transformer,deep-learning,pytorch,attention,moe,mixture-of-experts,inl-dynamics,flash-attention,mamba,rwkv
Classifier: Development Status :: 4 - Beta
Classifier: Intended Audience :: Developers
Classifier: Intended Audience :: Science/Research
Classifier: License :: Other/Proprietary License
Classifier: Programming Language :: Python :: 3
Classifier: Programming Language :: Python :: 3.8
Classifier: Programming Language :: Python :: 3.9
Classifier: Programming Language :: Python :: 3.10
Classifier: Programming Language :: Python :: 3.11
Classifier: Programming Language :: Python :: 3.12
Classifier: Topic :: Scientific/Engineering :: Artificial Intelligence
Requires-Python: >=3.8
License-File: LICENSE
Requires-Dist: torch>=2.0.0
Requires-Dist: numpy>=1.21.0
Requires-Dist: einops>=0.6.0
Provides-Extra: cuda
Requires-Dist: triton>=2.0.0; extra == "cuda"
Requires-Dist: flash-attn>=2.0.0; extra == "cuda"
Provides-Extra: all
Requires-Dist: triton>=2.0.0; extra == "all"
Requires-Dist: flash-attn>=2.0.0; extra == "all"
Requires-Dist: transformers>=4.30.0; extra == "all"
Requires-Dist: tokenizers>=0.13.0; extra == "all"
Requires-Dist: datasets>=2.0.0; extra == "all"
Requires-Dist: wandb>=0.15.0; extra == "all"
Provides-Extra: dev
Requires-Dist: pytest>=7.0.0; extra == "dev"
Requires-Dist: pytest-cov>=4.0.0; extra == "dev"
Requires-Dist: black>=23.0.0; extra == "dev"
Requires-Dist: ruff>=0.1.0; extra == "dev"
Dynamic: license-file
